WPP_Whatsapp/README.md
WPP_Whatsapp/__init__.py
WPP_Whatsapp/api/Whatsapp.py
WPP_Whatsapp/api/__init__.py
WPP_Whatsapp/api/const.py
WPP_Whatsapp/api/helpers/__init__.py
WPP_Whatsapp/api/helpers/decorators.py
WPP_Whatsapp/api/helpers/download_file.py
WPP_Whatsapp/api/helpers/function.py
WPP_Whatsapp/api/helpers/jsFunction.py
WPP_Whatsapp/api/helpers/scrap-img.py
WPP_Whatsapp/api/helpers/wa_version.py
WPP_Whatsapp/api/helpers/wapi.py
WPP_Whatsapp/api/layers/BusinessLayer.py
WPP_Whatsapp/api/layers/CatalogLayer.py
WPP_Whatsapp/api/layers/ControlsLayer.py
WPP_Whatsapp/api/layers/GroupLayer.py
WPP_Whatsapp/api/layers/HostLayer.py
WPP_Whatsapp/api/layers/LabelsLayer.py
WPP_Whatsapp/api/layers/ListenerLayer.py
WPP_Whatsapp/api/layers/ProfileLayer.py
WPP_Whatsapp/api/layers/RetrieverLayer.py
WPP_Whatsapp/api/layers/SenderLayer.py
WPP_Whatsapp/api/layers/StatusLayer.py
WPP_Whatsapp/api/layers/UILayer.py
WPP_Whatsapp/api/layers/__init__.py
WPP_Whatsapp/api/model/__init__.py
WPP_Whatsapp/api/model/status_find.py
WPP_Whatsapp/controllers/__init__.py
WPP_Whatsapp/controllers/auth.py
WPP_Whatsapp/controllers/browser.py
WPP_Whatsapp/controllers/init_multi.py
WPP_Whatsapp/controllers/initializer.py
WPP_Whatsapp/js_lib/wapi.js
WPP_Whatsapp/utils/__init__.py
WPP_Whatsapp/utils/ffmpeg.py
wpp_whatsapp-0.5.6.dist-info/licenses/LICENSE
wpp_whatsapp-0.5.6.dist-info/METADATA
wpp_whatsapp-0.5.6.dist-info/WHEEL
wpp_whatsapp-0.5.6.dist-info/top_level.txt
wpp_whatsapp-0.5.6.dist-info/RECORD
