Metadata-Version: 2.4
Name: WPP_Whatsapp
Version: 0.5.6
Summary: WPP_Whatsapp aim of exporting functions from WhatsApp Web to the python, which can be used to support the creation of any interaction, such as customer service, media sending, intelligence recognition based on phrases artificial and many other things, use your imagination
Home-page: https://github.com/3mora2/WPP_Whatsapp
Author: Ammar Alkotb
Author-email: ammar.alkotb@gmail.com
License: MIT License
Project-URL: Bug Report, https://github.com/3mora2/WPP_Whatsapp/issues/new
Classifier: License :: OSI Approved :: MIT License
Classifier: Intended Audience :: Developers
Classifier: Programming Language :: Python
Classifier: Topic :: Software Development :: Libraries :: Python Modules
License-File: LICENSE
Requires-Dist: event-emitter-js
Requires-Dist: playwright>=1.43.0
Requires-Dist: playwright-stealth
Requires-Dist: Pillow
Requires-Dist: psutil
Requires-Dist: pyee
Requires-Dist: segno
Requires-Dist: typing_extensions
Requires-Dist: node-semver
Requires-Dist: aiohttp
Requires-Dist: PlaywrightSafeThread>=0.5.5
Dynamic: author
Dynamic: author-email
Dynamic: classifier
Dynamic: description
Dynamic: description-content-type
Dynamic: home-page
Dynamic: license
Dynamic: license-file
Dynamic: project-url
Dynamic: requires-dist
Dynamic: summary
